datefactory.py
datefactory-1.0.1.dist-info/LICENSE
datefactory-1.0.1.dist-info/METADATA
datefactory-1.0.1.dist-info/WHEEL
datefactory-1.0.1.dist-info/top_level.txt
datefactory-1.0.1.dist-info/RECORD
