Metadata-Version: 2.1
Name: datefactory
Version: 1.0.1
Summary: Date Handling
Home-page: UNKNOWN
Author: Niall Stapleton
Author-email: niall.stapleton@gmail.com
License: UNKNOWN
Platform: UNKNOWN
Classifier: Programming Language :: Python :: 3
Classifier: License :: OSI Approved :: MIT License
Classifier: Operating System :: OS Independent
Requires-Python: >=3.6
